seriate.py
seriate-1.1.2.dist-info/LICENSE.md
seriate-1.1.2.dist-info/METADATA
seriate-1.1.2.dist-info/WHEEL
seriate-1.1.2.dist-info/top_level.txt
seriate-1.1.2.dist-info/RECORD
