Metadata-Version: 2.1
Name: seriate
Version: 1.1.2
Summary: Implementation of the Seriation sequence ordering algorithm.
Home-page: https://github.com/src-d/seriate
Author: source{d}
Author-email: machine-learning@sourced.tech
License: Apache-2.0
Download-URL: https://github.com/src-d/seriate
Keywords: seriation
Platform: UNKNOWN
Classifier: Development Status :: 5 - Production/Stable
Classifier: Intended Audience :: Developers
Classifier: License :: OSI Approved :: Apache Software License
Classifier: Programming Language :: Python :: 3.5
Classifier: Programming Language :: Python :: 3.6
Classifier: Programming Language :: Python :: 3.7
Classifier: Programming Language :: Python :: 3.8
Requires-Dist: numpy (>=1.0)
Requires-Dist: ortools (<8,>=6.7.4973)
Requires-Dist: packaging (>=16.0)
